src/__init__.py
src/ajum.py
src/cli.py
src/helpers.py
we_love_ajum-0.7.3.dist-info/LICENSE
we_love_ajum-0.7.3.dist-info/METADATA
we_love_ajum-0.7.3.dist-info/WHEEL
we_love_ajum-0.7.3.dist-info/entry_points.txt
we_love_ajum-0.7.3.dist-info/top_level.txt
we_love_ajum-0.7.3.dist-info/RECORD
